scholarscraper/__init__.py
scholarscraper/scraper.py
scholarlyscraper-0.1.0.dist-info/LICENSE
scholarlyscraper-0.1.0.dist-info/METADATA
scholarlyscraper-0.1.0.dist-info/WHEEL
scholarlyscraper-0.1.0.dist-info/top_level.txt
scholarlyscraper-0.1.0.dist-info/RECORD
