Metadata-Version: 2.1
Name: scholarlyscraper
Version: 0.1.0
Summary: A Python library for scraping Google Scholar profiles using Playwright
Author-email: Rach Pradhan <rach@rachit.ai>
Project-URL: Homepage, https://github.com/justrach/scholarscraper
Project-URL: Bug Tracker, https://github.com/justrach/scholarscraper/issues
Classifier: Programming Language :: Python :: 3
Classifier: License :: OSI Approved :: MIT License
Classifier: Operating System :: OS Independent
Requires-Python: >=3.8
License-File: LICENSE
Requires-Dist: playwright >=1.40.0
Requires-Dist: asyncio >=3.4.3
